[
    {
        "img": "../assets/img-sell/2572577.jpeg",
        "name": "Unlocked Instant Extensions Mascara",
        "value": "R$32.00"
    },
    {
        "img": "../assets/img-sell/2596644.jpeg",
        "name": "Tartelette Tubing Mascara",
        "value": "R$25.00"
    },
    {
        "img": "../assets/img-sell/2603635.jpeg",
        "name": "Better Than Sex Chocolate Volumizing & Lengthening Mascara",
        "value": "R$38.00"
    },
    {
        "img": "./assets/img-sell/2611811.jpeg",
        "name": "Le 8 Hypnôse Serum-Infused Volumizing Mascara",
        "value": "R$30.00"
    }
]