[
  {"name":"Unlocked Instant Extensions Mascara","value":"R$ 32.00","img":"./assets/products/assets/mascaras/1.jpeg"},
  {"name":"Tartelette Tubing Mascara","value":"R$ 25.00","img":"./assets/products/assets/mascaras/2.jpeg"},
  {"name":"Chocolate Volumizing","value":"R$ 38.00","img":"./assets/products/assets/mascaras/3.jpeg"},
  {"name":"Le 8 Hypnôse Mascara","value":"R$ 30.00","img":"./assets/products/assets/mascaras/4.jpeg"},
  {"name":"BADgal BANG! Volumizing Mascara","value":"R$ 29.00","img":"./assets/products/assets/mascaras/5.jpeg"},
  {"name":"Better Than Sex Volumizing","value":"R$ 29.00","img":"./assets/products/assets/mascaras/6.jpeg"},
  {"name":"Superhero Volumizing Waterproof Mascara","value":"R$ 19.00","img":"./assets/products/assets/mascaras/7.jpeg"},
  {"name":"Clinique Lash","value":"R$ 28.00","img":"./assets/products/assets/mascaras/8.jpeg"},
  {"name":"Essence Lash Princess Mascara","value":"R$ 24.00","img":"./assets/products/assets/mascaras/9.jpeg"},
  {"name":"Estée Lauder Little Black Primer","value":"R$ 23.00","img":"./assets/products/assets/mascaras/10.jpeg"},
  {"name":"Grande Cosmetics GrandePRIMER","value":"R$ 32.00","img":"./assets/products/assets/mascaras/11.jpeg"},
  {"name":"L'Oréal Voluminous Lengthening Lash Primer","value":"R$ 39.00","img":"./assets/products/assets/mascaras/12.jpeg"},
  {"name":"Lancôme Cils Booster XL Vitamin-Infused","value":"R$ 35.00","img":"./assets/products/assets/mascaras/13.jpeg"},
  {"name":"Morphe The Big Prime Conditioning Lash Primer","value":"R$ 17.00","img":"./assets/products/assets/mascaras/14.jpeg"},
  {"name":"Rabanne Famous Primer Mascara","value":"R$ 21.00","img":"./assets/products/assets/mascaras/15.jpeg"},
  {"name":"Too Faced Better Than Sex Foreplay Mascara","value":"R$ 28.00","img":"./assets/products/assets/mascaras/16.jpeg"},
  {"name":"Urban Decay Cosmetics Subversion Lash Primer","value":"R$ 21.00","img":"./assets/products/assets/mascaras/17.jpeg"},
  {"name":"Winky Lux First Swipe Conditioning Lash Primer","value":"R$ 28.00","img":"./assets/products/assets/mascaras/18.jpeg"}
]